hotspot/__init__.py
hotspot/core.py
hotspot/exceptions.py
hotspot/query.py
frauddi_hotspot-0.1.0.dist-info/METADATA
frauddi_hotspot-0.1.0.dist-info/WHEEL
frauddi_hotspot-0.1.0.dist-info/licenses/LICENSE
frauddi_hotspot-0.1.0.dist-info/RECORD
