Metadata-Version: 2.4
Name: frauddi-hotspot
Version: 0.1.0
Summary: Find data concentration patterns and hotspots. Built for fraud detection and risk analysis.
Project-URL: Homepage, https://github.com/frauddi/hotspot
Project-URL: Repository, https://github.com/frauddi/hotspot
Project-URL: Bug Tracker, https://github.com/frauddi/hotspot/issues
Author-email: Elio Rincón <elio@frauddi.com>
License-Expression: MIT
License-File: LICENSE
Keywords: anomaly-detection,data-analysis,fraud-detection,hotspots,pattern-mining
Classifier: Development Status :: 4 - Beta
Classifier: Intended Audience :: Developers
Classifier: License :: OSI Approved :: MIT License
Classifier: Operating System :: OS Independent
Classifier: Programming Language :: Python :: 3
Classifier: Programming Language :: Python :: 3.8
Classifier: Programming Language :: Python :: 3.9
Classifier: Programming Language :: Python :: 3.10
Classifier: Programming Language :: Python :: 3.11
Classifier: Programming Language :: Python :: 3.12
Classifier: Topic :: Scientific/Engineering :: Information Analysis
Classifier: Topic :: Security
Requires-Python: >=3.11
Provides-Extra: dev
Requires-Dist: black>=23.0; extra == 'dev'
Requires-Dist: isort>=6.0; extra == 'dev'
Requires-Dist: pytest-cov>=4.0; extra == 'dev'
Requires-Dist: pytest>=7.0; extra == 'dev'
Requires-Dist: ruff>=0.1.0; extra == 'dev'
